{
  "Parameters": {
    "AvailabilityZones": "us-east-2a, us-east-2b",
    "KeyPairName": "cfn-key-1",
    "PrivateSubnet1CIDR": "10.0.0.0/28",
    "PrivateSubnet2CIDR": "10.0.0.16/28",
    "PrivateSubnet3CIDR": "10.0.0.31/28",
    "PublicSubnet1CIDR": "10.0.0.46/28",
    "PublicSubnet2CIDR": "10.0.0.61/28",
    "PublicSubnet3CIDR": "10.0.0.76/28",
    "QSS3BucketName": "retinalyze-deployment",
    "QSS3KeyPrefix": "prefix",
    "VPCCIDR": "10.0.0.0/24",

    "MySQLInstanceName": "retinalyze-test",
    "DatabasePassword": "123456",
    "AllocatedStorage": "100",
    "MySQLVersion": "latest8",
    "DBInstanceClass": "db.m5.large"
  }
}